CHANGELOG.rst
LICENSE
MANIFEST.in
README.rst
VERSION
setup.py
Flask_Velox.egg-info/PKG-INFO
Flask_Velox.egg-info/SOURCES.txt
Flask_Velox.egg-info/dependency_links.txt
Flask_Velox.egg-info/not-zip-safe
Flask_Velox.egg-info/requires.txt
Flask_Velox.egg-info/top_level.txt
dependencies/dev.txt
dependencies/install.txt
dependencies/test.txt
flask_velox/__init__.py
flask_velox/fields.py
flask_velox/formatters.py
flask_velox/admin/__init__.py
flask_velox/admin/mixins/__init__.py
flask_velox/admin/mixins/forms.py
flask_velox/admin/mixins/template.py
flask_velox/admin/mixins/sqla/__init__.py
flask_velox/admin/mixins/sqla/delete.py
flask_velox/admin/mixins/sqla/read.py
flask_velox/admin/views/__init__.py
flask_velox/admin/views/forms.py
flask_velox/admin/views/template.py
flask_velox/admin/views/sqla/__init__.py
flask_velox/admin/views/sqla/delete.py
flask_velox/admin/views/sqla/forms.py
flask_velox/admin/views/sqla/read.py
flask_velox/mixins/__init__.py
flask_velox/mixins/context.py
flask_velox/mixins/forms.py
flask_velox/mixins/http.py
flask_velox/mixins/template.py
flask_velox/mixins/sqla/__init__.py
flask_velox/mixins/sqla/delete.py
flask_velox/mixins/sqla/forms.py
flask_velox/mixins/sqla/object.py
flask_velox/mixins/sqla/read.py
flask_velox/templates/velox/admin/create.html
flask_velox/templates/velox/admin/delete.html
flask_velox/templates/velox/admin/delete_multiple.html
flask_velox/templates/velox/admin/table.html
flask_velox/templates/velox/admin/update.html
flask_velox/templates/velox/admin/update_multi_form.html
flask_velox/templates/velox/lib/delete.html
flask_velox/templates/velox/lib/forms.html
flask_velox/views/__init__.py
flask_velox/views/forms.py
flask_velox/views/http.py
flask_velox/views/template.py
flask_velox/views/sqla/__init__.py
flask_velox/views/sqla/delete.py
flask_velox/views/sqla/forms.py
flask_velox/views/sqla/read.py