Metadata-Version: 1.1
Name: Flask-Velox
Version: 2014.04.24.2
Summary: Velox is a set of classes & mixins to help rapidly build Flask applications.
Home-page: https://github.com/thisissoon/Flask-Velox
Author: SOON_
Author-email: dorks@thisissoon.com
License: UNKNOWN
Platform: UNKNOWN
Classifier: Environment :: Web Environment
Classifier: Intended Audience :: Developers
Classifier: Development Status :: 3 - Alpha
Classifier: License :: OSI Approved :: MIT License
Classifier: Operating System :: OS Independent
Classifier: Programming Language :: Python
Classifier: Programming Language :: Python :: 2.7
Classifier: Topic :: Software Development
Classifier: Topic :: Software Development :: Libraries :: Python Modules
Classifier: Topic :: Internet :: WWW/HTTP :: Dynamic Content
